examples/etl_sample_dag.py
examples/profiles_sample_dag.py
examples/retl_sample_dag.py
rudder_airflow_provider/__init__.py
rudder_airflow_provider/hooks/__init__.py
rudder_airflow_provider/hooks/rudderstack.py
rudder_airflow_provider/operators/__init__.py
rudder_airflow_provider/operators/rudderstack.py
rudderstack_airflow_provider-2.4.2.dist-info/licenses/LICENSE
rudderstack_airflow_provider-2.4.2.dist-info/METADATA
rudderstack_airflow_provider-2.4.2.dist-info/WHEEL
rudderstack_airflow_provider-2.4.2.dist-info/entry_points.txt
rudderstack_airflow_provider-2.4.2.dist-info/top_level.txt
rudderstack_airflow_provider-2.4.2.dist-info/RECORD
