Metadata-Version: 2.4
Name: rudderstack-airflow-provider
Version: 2.4.2
Summary: Apache airflow provider for managing Reverse ETL syncs and Profiles runs in RudderStack.
License: MIT License
Keywords: airflow,orchestration,rudderstack
Classifier: Framework :: Apache Airflow
Classifier: Framework :: Apache Airflow :: Provider
Requires-Python: >=3.11
License-File: LICENSE
Requires-Dist: apache-airflow>=2.10.0
Requires-Dist: apache-airflow-providers-http>=5.0.0
Requires-Dist: pytest>=7.3.1
Requires-Dist: requests>=2.32.3
Requires-Dist: responses>=0.25.0
Requires-Dist: setuptools>=80.0.0
Requires-Dist: zipp>=3.19.1
Requires-Dist: ruff>=0.6.8
Dynamic: license-file
